{
  "resourceType": "MedicationKnowledge",
  "id": "berberine",
  "meta": {
    "profile": [
      "http://hl7.org/fhir/StructureDefinition/MedicationKnowledge"
    ]
  },
  "status": "active",
  "code": {
    "coding": [
      {
        "system": "https://twtxgnn.yao.care/drugs",
        "code": "berberine",
        "display": "Berberine"
      }
    ],
    "text": "Berberine"
  },
  "intendedJurisdiction": [
    {
      "coding": [
        {
          "system": "urn:iso:std:iso:3166",
          "code": "TW",
          "display": "Taiwan"
        }
      ]
    }
  ],
  "extension": [
    {
      "url": "https://twtxgnn.yao.care/fhir/StructureDefinition/evidence-level",
      "valueCode": "L3"
    }
  ],
  "indicationGuideline": [
    {
      "indication": [
        {
          "reference": {
            "display": "腹瀉、急慢性腸炎、腸內異常醱酵、細菌性痢疾"
          }
        }
      ]
    }
  ]
}