{
  "resourceType": "MedicationKnowledge",
  "id": "remdesivir",
  "meta": {
    "profile": [
      "http://hl7.org/fhir/StructureDefinition/MedicationKnowledge"
    ]
  },
  "status": "active",
  "code": {
    "coding": [
      {
        "system": "https://twtxgnn.yao.care/drugs",
        "code": "remdesivir",
        "display": "Remdesivir"
      }
    ],
    "text": "Remdesivir"
  },
  "intendedJurisdiction": [
    {
      "coding": [
        {
          "system": "urn:iso:std:iso:3166",
          "code": "TW",
          "display": "Taiwan"
        }
      ]
    }
  ],
  "extension": [
    {
      "url": "https://twtxgnn.yao.care/fhir/StructureDefinition/evidence-level",
      "valueCode": "L1"
    }
  ],
  "indicationGuideline": [
    {
      "indication": [
        {
          "reference": {
            "display": "適應症變更：\r\n１、類風濕性關節炎：合併methotrexate 或其他傳統型疾病緩解型抗風濕藥物(..."
          }
        }
      ]
    }
  ]
}