{
  "generated": "2026-05-21T06:43:39.452673+00:00",
  "count": 13,
  "news": [
    {
      "id": "e1ac859d2a44",
      "title": "台中疫苗補助卡關長者「皮蛇」纏身痛如酷刑- 生活",
      "published": "2026-05-21T05:31:00+00:00",
      "sources": [
        {
          "name": "工商時報",
          "link": "https://news.google.com/rss/articles/CBMiX0FVX3lxTE1pQTZaMkRCR2NFM293ZkxJVmNudGZuV29wN2lKQnptLVl1ZmduUjV1UVRsTEFteGFWb3lCaEZvMlVKZEFOeUhoeHJKdHRDSUd3RnllSW5kUllLazBBNmVF?oc=5"
        }
      ],
      "keywords": [
        {
          "type": "indication",
          "name": "generic_cancer",
          "keyword": "癌症",
          "related_drugs": [
            {
              "slug": "trabectedin",
              "name": "Trabectedin"
            },
            {
              "slug": "cytarabine",
              "name": "Cytarabine"
            },
            {
              "slug": "docetaxel",
              "name": "Docetaxel"
            },
            {
              "slug": "acitretin",
              "name": "Acitretin"
            },
            {
              "slug": "tinidazole",
              "name": "Tinidazole"
            },
            {
              "slug": "regorafenib",
              "name": "Regorafenib"
            },
            {
              "slug": "irbesartan",
              "name": "Irbesartan"
            },
            {
              "slug": "paclitaxel",
              "name": "Paclitaxel"
            },
            {
              "slug": "cladribine",
              "name": "Cladribine"
            },
            {
              "slug": "oteracil",
              "name": "Oteracil"
            },
            {
              "slug": "amcinonide",
              "name": "Amcinonide"
            },
            {
              "slug": "temozolomide",
              "name": "Temozolomide"
            },
            {
              "slug": "gefitinib",
              "name": "Gefitinib"
            },
            {
              "slug": "vinorelbine",
              "name": "Vinorelbine"
            },
            {
              "slug": "felodipine",
              "name": "Felodipine"
            },
            {
              "slug": "acebutolol",
              "name": "Acebutolol"
            },
            {
              "slug": "metoprolol",
              "name": "Metoprolol"
            },
            {
              "slug": "hydroxyprogesterone_caproate",
              "name": "Hydroxyprogesterone caproate"
            },
            {
              "slug": "durvalumab",
              "name": "Durvalumab"
            },
            {
              "slug": "atezolizumab",
              "name": "Atezolizumab"
            },
            {
              "slug": "berberine",
              "name": "Berberine"
            },
            {
              "slug": "ipilimumab",
              "name": "Ipilimumab"
            },
            {
              "slug": "clobetasone",
              "name": "Clobetasone"
            },
            {
              "slug": "carbenoxolone",
              "name": "Carbenoxolone"
            },
            {
              "slug": "pralatrexate",
              "name": "Pralatrexate"
            },
            {
              "slug": "interferon_beta-1b",
              "name": "Interferon beta-1b"
            },
            {
              "slug": "omalizumab",
              "name": "Omalizumab"
            },
            {
              "slug": "nebivolol",
              "name": "Nebivolol"
            },
            {
              "slug": "dehydrocholic_acid",
              "name": "Dehydrocholic acid"
            },
            {
              "slug": "avelumab",
              "name": "Avelumab"
            },
            {
              "slug": "disopyramide",
              "name": "Disopyramide"
            },
            {
              "slug": "carboplatin",
              "name": "Carboplatin"
            },
            {
              "slug": "gemcitabine",
              "name": "Gemcitabine"
            },
            {
              "slug": "acetazolamide",
              "name": "Acetazolamide"
            },
            {
              "slug": "bevacizumab",
              "name": "Bevacizumab"
            },
            {
              "slug": "mannitol",
              "name": "Mannitol"
            },
            {
              "slug": "levamisole",
              "name": "levamisole"
            },
            {
              "slug": "oxytetracycline",
              "name": "Oxytetracycline"
            },
            {
              "slug": "bempedoic_acid",
              "name": "Bempedoic acid"
            },
            {
              "slug": "ramucirumab",
              "name": "Ramucirumab"
            },
            {
              "slug": "cefmetazole",
              "name": "Cefmetazole"
            },
            {
              "slug": "benazepril",
              "name": "Benazepril"
            },
            {
              "slug": "vismodegib",
              "name": "Vismodegib"
            },
            {
              "slug": "anastrozole",
              "name": "Anastrozole"
            },
            {
              "slug": "pemetrexed",
              "name": "Pemetrexed"
            },
            {
              "slug": "hydroxyurea",
              "name": "Hydroxyurea"
            },
            {
              "slug": "zanubrutinib",
              "name": "Zanubrutinib"
            }
          ]
        },
        {
          "type": "indication",
          "name": "herpes zoster",
          "keyword": "皮蛇",
          "related_drugs": [
            {
              "slug": "avelumab",
              "name": "Avelumab"
            }
          ]
        },
        {
          "type": "indication",
          "name": "生蛇",
          "keyword": "生蛇",
          "related_drugs": [
            {
              "slug": "avelumab",
              "name": "Avelumab"
            }
          ]
        },
        {
          "type": "indication",
          "name": "神經痛",
          "keyword": "神經痛",
          "related_drugs": [
            {
              "slug": "ibuprofen",
              "name": "Ibuprofen"
            },
            {
              "slug": "salicylamide",
              "name": "Salicylamide"
            }
          ]
        }
      ]
    },
    {
      "id": "38fbf0a2e385",
      "title": "照護線上》給寶寶的第一份見面禮，呼吸道細胞融合病毒（RSV）長效型單株抗體「出生即防護」策略解析，專科醫師圖文懶人包",
      "published": "2026-05-21T00:00:00+00:00",
      "sources": [
        {
          "name": "自由評論網",
          "link": "https://news.google.com/rss/articles/CBMiYkFVX3lxTE1iWlJjVS12MUJlQ0Y0ZmlaWENrS3FuYy0tYlN3NUY0UDlkaURoRWNtWDhLVkNSWnowbDNlT3BCcVdDRkNObTBmczdhV0VQd0d5TjJrN3B3Q25QS1VfTFZrZXJR0gFnQVVfeXFMTk5hWndjeUQ1TjY0SXF2V2t1eWJFcWUtYzdreDlEdzZmOG5VZlhsR1FqcWROVjRvU0lCT3hwNVFIRFduNkZieEllaS1PNk0xS0tGS0pQLWtmQk56Qk5mdHVDUFdHZmNaNA?oc=5"
        }
      ],
      "keywords": [
        {
          "type": "indication",
          "name": "common cold",
          "keyword": "感冒",
          "related_drugs": [
            {
              "slug": "salicylamide",
              "name": "Salicylamide"
            }
          ]
        }
      ]
    },
    {
      "id": "3573b1d7f763",
      "title": "保健》防子宮頸癌 醫籲打HPV疫苗",
      "published": "2026-05-20T20:10:00+00:00",
      "sources": [
        {
          "name": "中時新聞網",
          "link": "https://news.google.com/rss/articles/CBMia0FVX3lxTE94SHEzbU5RRUZWU3I4N2tXcmxiTTFZYnE5SlNaOEJWVnZXNXJuRlRmYnZNNlBVTXBTa3RlRUo3d0lEd1NqU08wUFlRbVZvVTJaYVBfRVllYWpKX2FlVUJRYWNEYVRFX2d0VlFj?oc=5"
        }
      ],
      "keywords": [
        {
          "type": "indication",
          "name": "子宮頸癌",
          "keyword": "子宮頸癌",
          "related_drugs": [
            {
              "slug": "paclitaxel",
              "name": "Paclitaxel"
            }
          ]
        }
      ]
    },
    {
      "id": "edad4cd6135c",
      "title": "科學家發現了阿茲海默症的隱藏誘因並將其關閉",
      "published": "2026-05-20T13:32:32+00:00",
      "sources": [
        {
          "name": "arch-web.com.tw",
          "link": "https://news.google.com/rss/articles/CBMi-gJBVV95cUxNaU5JY0gzWVl6aUZaRGJMZDA4blFMSXJYcDRJUkdQbzNmZmwxWXpNTTJBRzBXLTl4M254bWVsMzQ3c2ppU1FyeDhWNGVNdXdmdTEtbENMSkk0R0JnemtHaXhJd1g0R1lVSnVSQ2ZkNjliZE00QURleTItbVRJZVlDdGgtV3RkcTRWTlhFWVhVLWdPQ0NTT0MyRkVGRmxDNWRLM0FNYV9LY0p2Yy1RY3VNTXRPbTEyWkhUR3lRYUdyWjlSUGNYT09oOHFpQ1F5a2RIMkgteEV3QmZEckRxUi12bk9fRkNJdWZtUlFBYWNaTVdVRGE2dG5HQWVlOU5CUXVaUm1IVWFELVpTdkE5Q1FnMkt1X0F1MHZOY0NyU3VqWVNGSVR0R1pqYTRWUGM0c21ndjBiQmZMOFYwRzAtcHIwVllzdHdocm9LT0pSNzFGcjBLSF9DTWU4UzVESTZ1MzhaY2h0OVZFalVxMGJmTjk0YU0xTmdOYmI4bkE?oc=5"
        }
      ],
      "keywords": [
        {
          "type": "indication",
          "name": "dementia",
          "keyword": "阿茲海默症",
          "related_drugs": [
            {
              "slug": "gefitinib",
              "name": "Gefitinib"
            }
          ]
        }
      ]
    },
    {
      "id": "bbb9a5f07b9c",
      "title": "失智症新發現：孤獨、失眠為風險因子 血液檢測助早期篩檢",
      "published": "2026-05-20T12:19:59+00:00",
      "sources": [
        {
          "name": "yesmedia.com.tw",
          "link": "https://news.google.com/rss/articles/CBMizAJBVV95cUxQOFB1aWVIcjJXbE84cjFGZDhxRkJ1R0xFZl9xZFN2UXkwWHo3V2VHVzFaazMxWEhhNzVvd3lNV1ZUTE1wMU1sSEdVVjFSTktHblJiaTZDcHpKQkd3cVVya0tMZDFzb0ZIZ051TG9PeXFJRWxMLWVnUFdEUEtCdVEyR1NibXQxWXA5ZUktM3NSSGNHUVI1S3NsXy12dFRsR1pPbVRBdHJ5YjA3OE8wYW15RnBqaE91ZHR0NzJBTy1kb0k1TTFGMTl1ekM2Nl8yMWxBQm9VR09ySkVxbzVzZVFCejJ4UzV5a2VjaXo2M3p1WVhxUVRLYmx0dU5IbksxWXlDZXV3X3JJQUZoMkJBNDhJVVNBa2FKZmdWWWVTNWZuWXZuWV9xQkRyWmVZdWxJVmdReDBIS2lOZTFvM0FZU1ZpRVZ1eFh4TFh1bnRndw?oc=5"
        }
      ],
      "keywords": [
        {
          "type": "indication",
          "name": "dementia",
          "keyword": "失智症",
          "related_drugs": [
            {
              "slug": "gefitinib",
              "name": "Gefitinib"
            }
          ]
        },
        {
          "type": "indication",
          "name": "失智",
          "keyword": "失智",
          "related_drugs": [
            {
              "slug": "gefitinib",
              "name": "Gefitinib"
            }
          ]
        }
      ]
    },
    {
      "id": "01fed18a1f24",
      "title": "女性更易失智！風險比男性高2倍 醫點名5大傷腦地雷 50歲後必看護腦方式 - TVBS 健康2.0",
      "published": "2026-05-20T10:38:00+00:00",
      "sources": [
        {
          "name": "TVBS 健康2.0",
          "link": "https://news.google.com/rss/articles/CBMiUkFVX3lxTE9HNXFReGVydmNXVUVHMnRHamhiX1ZMQWJ5QXlWVVdlSGtkU1ZwcC1nOWNvcG5FVWtTSTV5a2l6U0Z1VW1vNkdsZERrZ192OXctaUE?oc=5"
        }
      ],
      "keywords": [
        {
          "type": "indication",
          "name": "dementia",
          "keyword": "失智",
          "related_drugs": [
            {
              "slug": "gefitinib",
              "name": "Gefitinib"
            }
          ]
        }
      ]
    },
    {
      "id": "3ebc255b60c7",
      "title": "講話常「嗯」、「啊」別只當口頭禪 說話方式恐暗藏失智風險",
      "published": "2026-05-20T09:53:10+00:00",
      "sources": [
        {
          "name": "科技島",
          "link": "https://news.google.com/rss/articles/CBMiX0FVX3lxTE56ODQ4bHAxMWEzTGJQaWRQTUJDdmRnUGw2UVVsYkVLd1BJRkw5bW1GRkFxRi1kQU5ieURZcTlwZjk0OU93V3dWTXpHaDVxOWVNWVJVUUQzQ0QzcWQ3MHBr?oc=5"
        }
      ],
      "keywords": [
        {
          "type": "indication",
          "name": "dementia",
          "keyword": "失智",
          "related_drugs": [
            {
              "slug": "gefitinib",
              "name": "Gefitinib"
            }
          ]
        }
      ]
    },
    {
      "id": "68a77656a358",
      "title": "腦退化先兆｜老人家常跌親響健康警號 失智風險暴增74% 研究：最快1年內確診【附腦退化徵兆】",
      "published": "2026-05-20T09:00:55+00:00",
      "sources": [
        {
          "name": "香港經濟日報HKET",
          "link": "https://news.google.com/rss/articles/CBMizwRBVV95cUxOVzVBOEFoNk1mMnA5Mk1taktjZ2RjRkJBQVlLQ1pGaXUzSVJ6YlF4WHBQTnpxSllSM3QySVRDVlZJNzZHN1lvSVk3aG92S2E3WlJCcVc1eHJzNHI1Z0FrX0U3MERrZmRSVndCdjVPVmJCZlozdVJ0Sk1hWFpZWHFtcHYwTDNTSnNXMmZtZ2l1T3pRNjY1UmlKNHVzVGhvTWF3a1Y0Y1hrLXZBVlU5aUxyRmNBcWs1NHhXZGFwajJpSUktanJrV0xvQTk2c3pjRzZKSG1sWlYzRUZpd0FnaS1rY0ZKVGFaZDNIV054WmpFLS1oNW91ZXRJdXdSem1KOWZnVWV5d3ZWUlhRRDNLbTVham9kRmp6MXpVbTRZanRVbEFoRDZ3dUVkLVBIc3JnajUwRFVzcnRIQmp6bk9Falh5UVhfVVZNb2xXQU1xLUdtam9MLVFXbEVjYjg5YUJyQ1hsNkRhcUZhVXhHYTdMRng4Uzd0YzFFUmVOVWZsM0xaR1ZGZFBmVnpYdVZUVnlRZFBQSG53c3NhWkh0VU51NjlQb3dldHJQcVFXbTlZM28yZlRkOWpVV3BKY2cxWFk4QnZxdXYzTHNRRFFvQWM2dWp0Mk00NnhLT2l2UVFyZ2RsMktlSjltWUlYZjFVRS1FM1BzMWJKNEtLQkNpODFsTnFzYzNUYU1PTjNiRnNUSXhiY1pReFJ5MUlzODJmR0cwZWM2ZmJiMG9QWlUzeEhZNU96MkMwNzFua25EdnNfTDFnNE91bXk4RWhITFVYMDlhMTQ?oc=5"
        }
      ],
      "keywords": [
        {
          "type": "indication",
          "name": "dementia",
          "keyword": "失智",
          "related_drugs": [
            {
              "slug": "gefitinib",
              "name": "Gefitinib"
            }
          ]
        }
      ]
    },
    {
      "id": "704455df3b95",
      "title": "市民50歲起可參與大腸癌篩查 提防大腸瘜肉變腸癌 - 晴報 Sky Post",
      "published": "2026-05-20T07:32:47+00:00",
      "sources": [
        {
          "name": "晴報 Sky Post",
          "link": "https://news.google.com/rss/articles/CBMiS0FVX3lxTFBfQnZRb3ZhTWVWTnlvRDZTcEhocTZ6eFVDTlRKZnN5ZUVKMVlEV3o4STR6VjF1RVB5OGR5VlgxenotM3gtU1p1Ylk5QQ?oc=5"
        }
      ],
      "keywords": [
        {
          "type": "indication",
          "name": "colonic neoplasm",
          "keyword": "大腸癌",
          "related_drugs": [
            {
              "slug": "oteracil",
              "name": "Oteracil"
            }
          ]
        },
        {
          "type": "indication",
          "name": "腸癌",
          "keyword": "腸癌",
          "related_drugs": [
            {
              "slug": "oteracil",
              "name": "Oteracil"
            },
            {
              "slug": "carboplatin",
              "name": "Carboplatin"
            },
            {
              "slug": "gemcitabine",
              "name": "Gemcitabine"
            },
            {
              "slug": "hydroxyurea",
              "name": "Hydroxyurea"
            }
          ]
        }
      ]
    },
    {
      "id": "511d6ed22a78",
      "title": "腸胃炎忌食稀飯！醫生指或刺激胃酸加重腹瀉 推介3 食物代替",
      "published": "2026-05-19T23:00:21+00:00",
      "sources": [
        {
          "name": "巴士的報",
          "link": "https://news.google.com/rss/articles/CBMi8AJBVV95cUxNN3RUeFNBSHF0dTlGd2FGR0VGVWd4SDlmLWVvVlpZUmNtMHZEbV93NWp5LTBVVkRCUTNOXzJKT0tMUmtqNHU4OVRMdFlnUExJajNlTGV4YzRjUkE0MFU5UmVMWGhsRGlYV0ZodFJaSGItRklkd0s2ejFXWVp4M2psWlM3S05iNndQMURieHVmSGItODBjNkJVSGgtMTlkSGNyWEZySnNlMy1MRlR3cHR4ODR6RUloTWNzYy01RFdUZGUzY3o4Wm84c19xeTExTm5feHN4YjVLVlJRdXdrTjVwT0cxa1gxVzF2UTFTUDBvU2lzZjE3bG42SW9iSW1pZWQ1bVZWZ3p4T2Q3QURoU1JUVk9OMlQxUkVkN0dLc2ZTTVQxNjRGVFFuQjJTVnp3UldtdDJ0VnNRel9SMXlnLXJuZGJvaWVJUV9OcGRUbFc4MkVENnZTazZ2Vlo4NGhwbXRocDJEVVRzQWc2Nm1ZWHJadA?oc=5"
        }
      ],
      "keywords": [
        {
          "type": "indication",
          "name": "胃炎",
          "keyword": "胃炎",
          "related_drugs": [
            {
              "slug": "aluminum_hydroxide",
              "name": "Aluminum hydroxide"
            },
            {
              "slug": "aluminum_oxide",
              "name": "Aluminum oxide"
            },
            {
              "slug": "propantheline",
              "name": "Propantheline"
            }
          ]
        },
        {
          "type": "indication",
          "name": "腹瀉",
          "keyword": "腹瀉",
          "related_drugs": [
            {
              "slug": "berberine",
              "name": "Berberine"
            }
          ]
        }
      ]
    },
    {
      "id": "9a65a5e35589",
      "title": "抗癌蔬菜︱紅肉吃太多恐致癌！ 營養師大推神級解毒菜 抗炎兼防癌食4星期見效",
      "published": "2026-05-19T10:47:39+00:00",
      "sources": [
        {
          "name": "香港經濟日報HKET",
          "link": "https://news.google.com/rss/articles/CBMikARBVV95cUxNeTBOVkNGNXdXRkQzYk0xLW9mWHFleGdVdVZqdEFvb0prUTRvaG5fNjQwM2dJNmV5dGczVFVJMUE3emVCRlR0Z3VYcWw1YUc0WTlwcldJWWFSZ3kwal8tSmtKWi1oRkk0d3Y5N0h2MnhMWnV3TGZTU1U3R05kcU5rTWczWnd3LWxJUHB4ckJTWnpYSEVNa2RlZWl5b1ZQWWhHdFJBbTJSYV9KQ3phVDdyODFVa2tHdlRXY0lpbWZwTWprTzdlVU9zWFdSTTEwZFJRN1hsTnZlbmxyb0Zza0YzRjltWWVjYzhpQTBnU0hKUlQ4X2tvT1hfTF84M0RQdUFZa1djX3RaSkRZd3RzOU02aEUya0NFem1VTlJxSGJvUFY0V1E4d3BuLVA4YnV3VURyZTAtY3k4M2YxSDRnUkRfd0Nra1pSY2VoTVFBbTlvSG0zdXlkaTA0NDZGUGpHSUZPaGE0SEFVdW5Ody1TS3NzcUhldTk1RFFCTV9jUGhiU3ByY3lfd250enFVQ3liU1B6UUppQ0tuRnFDbVA2Ujd4TkFHSlFDckwwM256X0RVNTdpLUNDeDVVODNtSFZrRTNpMkJQTXFWcHp4dGhqTlNhRHdYbWNNcVFDQmFFeGtBaGZKN1JBbWVUYjRuRFJEVU9YWm5LSnVfeHRfdGdjWlA4WEpaNHNyMVAyOXpfX3ZDNmI?oc=5"
        }
      ],
      "keywords": [
        {
          "type": "indication",
          "name": "colonic neoplasm",
          "keyword": "大腸癌",
          "related_drugs": [
            {
              "slug": "oteracil",
              "name": "Oteracil"
            }
          ]
        },
        {
          "type": "indication",
          "name": "腸癌",
          "keyword": "腸癌",
          "related_drugs": [
            {
              "slug": "oteracil",
              "name": "Oteracil"
            },
            {
              "slug": "carboplatin",
              "name": "Carboplatin"
            },
            {
              "slug": "gemcitabine",
              "name": "Gemcitabine"
            },
            {
              "slug": "hydroxyurea",
              "name": "Hydroxyurea"
            }
          ]
        }
      ]
    },
    {
      "id": "3b3e18f751e3",
      "title": "癲癇發作「塞湯匙」防咬舌？急診醫示警「這些動作超危險」：送醫前必做的5件救命小事",
      "published": "2026-05-19T06:52:00+00:00",
      "sources": [
        {
          "name": "幸福熟齡",
          "link": "https://news.google.com/rss/articles/CBMie0FVX3lxTFAyQk5ZZUwwSnp2X2c4R0R4di1nTGwxdkxrR0YwZnM5LVp0TW1ab3F0QjBkWmRTV3BnQXo3aXRaa2NkZkNlV0FsUzE5bzdsMnB5MnNneHNNNlJfUGVGcVRLcW94OWV1Zm4xVTdQcEx6Vkp4eHNEQ05ENVdXaw?oc=5"
        }
      ],
      "keywords": [
        {
          "type": "indication",
          "name": "癲癇",
          "keyword": "癲癇",
          "related_drugs": [
            {
              "slug": "acetazolamide",
              "name": "Acetazolamide"
            }
          ]
        }
      ]
    },
    {
      "id": "28903acb08ef",
      "title": "長壽基因或保護腦細胞 降低老化與失智症風險",
      "published": "2026-05-19T06:06:00+00:00",
      "sources": [
        {
          "name": "自由健康網",
          "link": "https://news.google.com/rss/articles/CBMiZEFVX3lxTE5hQVJzaEtwemtRelRBLTMwN2IxUDE4THBNMUZuWTZoOG15b2VXLVF2MVh1NlVMVnNBa3dISXJzYTRJQ3Fkb29NaXh5SHkzNVVnWGxFdVN2cEhrY3g0T21Ccl9pTGLSAWpBVV95cUxOM0FLWDNWdkVHWXFsSXBRVUU3ekVXUzJkRnQ0TkY5THZhS2tQSmlyNUltVTM1ejRqRlg4RW5Jc0UxM3VHeXhHWnNaTW9rTldrekdaVzhiakNLUUlXWW9HNDZRT0FmZmVlU1NB?oc=5"
        }
      ],
      "keywords": [
        {
          "type": "indication",
          "name": "dementia",
          "keyword": "失智症",
          "related_drugs": [
            {
              "slug": "gefitinib",
              "name": "Gefitinib"
            }
          ]
        },
        {
          "type": "indication",
          "name": "失智",
          "keyword": "失智",
          "related_drugs": [
            {
              "slug": "gefitinib",
              "name": "Gefitinib"
            }
          ]
        }
      ]
    }
  ]
}