{
  "generated": "2026-06-08T00:00:15.789136+00:00",
  "count": 1,
  "news": [
    {
      "id": "71f3f3cfee49",
      "title": "研究曝「1常見食物」能防骨折！效果堪比藥物 還沒副作用 | 三立新聞網 - LINE TODAY",
      "published": "2026-06-07T05:48:16+00:00",
      "sources": [
        {
          "name": "LINE TODAY",
          "link": "https://news.google.com/rss/articles/CBMiVkFVX3lxTFBGdFJMY0p3RUVwT1cwNDh1NFNfbWNaTk1xVWFtMHdYY25oRU5tb3BwdjVDMkcxMWVVcUFfRVhVd1h2MmdFNTRCVDlMLVRZT3R4MEZVOFhB?oc=5"
        }
      ],
      "keywords": [
        {
          "type": "indication",
          "name": "menopause",
          "keyword": "更年期",
          "related_drugs": [
            {
              "slug": "tinidazole",
              "name": "Tinidazole"
            },
            {
              "slug": "paclitaxel",
              "name": "Paclitaxel"
            },
            {
              "slug": "tioconazole",
              "name": "Tioconazole"
            },
            {
              "slug": "nystatin",
              "name": "Nystatin"
            }
          ]
        }
      ]
    }
  ]
}